geekgcc/KGCC.py
geekgcc/__init__.py
geekgcc-0.2.0.dist-info/licenses/LICENSE
geekgcc-0.2.0.dist-info/METADATA
geekgcc-0.2.0.dist-info/WHEEL
geekgcc-0.2.0.dist-info/top_level.txt
geekgcc-0.2.0.dist-info/RECORD
