Metadata-Version: 2.4
Name: geekgcc
Version: 0.2.0
Summary: Köppen-Geiger Climate Classification in Google Earth Engine
Author-email: Andrew Fullhart <andrew.fullhart@gmail.com>
License-Expression: MIT
Project-URL: Homepage, https://github.com/ARS-SWRC/GEE-KGCC
Project-URL: Issues, https://github.com/ARS-SWRC/GEE-KGCC
Classifier: Programming Language :: Python :: 3
Classifier: Operating System :: OS Independent
Requires-Python: >=3.9
License-File: LICENSE
Requires-Dist: earthengine-api
Dynamic: license-file
